hobot_vio_rdkx5/__init__.py
hobot_vio_rdkx5/libhbspdev.so
hobot_vio_rdkx5/libsrcampy.so
hobot_vio_rdkx5-3.0.6.dist-info/METADATA
hobot_vio_rdkx5-3.0.6.dist-info/WHEEL
hobot_vio_rdkx5-3.0.6.dist-info/top_level.txt
hobot_vio_rdkx5-3.0.6.dist-info/RECORD
