Metadata-Version: 2.1
Name: hobot-vio-rdkx5
Version: 3.0.6
Summary: python API for VIO
Home-page: UNKNOWN
Author: d-robotics
Author-email: technical_support@d-robotics.cc
License: UNKNOWN
Platform: UNKNOWN
Classifier: Operating System :: POSIX :: Linux
Classifier: License :: OSI Approved :: MIT License
Classifier: Intended Audience :: Developers
Classifier: Programming Language :: Python :: 3.10
Classifier: Topic :: Software Development
Classifier: Topic :: System :: Hardware
